{
  "title": "WE Learn B1U8 Festivals iWords 词汇填空",
  "exported_at": "2026-07-05T14:15:27.495657",
  "source": "WE Learn iWords 截图整理",
  "unit": "B1U8 Festivals",
  "quiz_type": "iwords_fill",
  "questions": [
    {
      "sort": 1,
      "type": "填空题(客观)",
      "title": "【B1U8 Festivals · iWords A】【中→英】\n适逢，与（某一天）重合\n请填写英文：______",
      "options": [
        ""
      ],
      "correct_answer": "fall on",
      "your_answer": "",
      "score": "0",
      "full_score": 1,
      "fill_hint": "填英文单词，小写即可；短语按原样填写",
      "memory": {
        "en": "fall on",
        "zh": "适逢，与（某一天）重合",
        "pos": "",
        "phonetic": "",
        "pattern": "zh2en",
        "unit_tag": "【B1U8 Festivals · iWords A】",
        "lang": "en",
        "hook": "「适逢」→ fall on（6 字母，首字母 F）",
        "fill_hint": "填英文单词，小写即可；短语按原样填写",
        "remix_pattern": "en2zh"
      }
    },
    {
      "sort": 2,
      "type": "填空题(客观)",
      "title": "【B1U8 Festivals · iWords A】【英→中】\nlunar  ['luːnə]  adj.\n中文释义：______",
      "options": [
        ""
      ],
      "correct_answer": "阴历的",
      "your_answer": "",
      "score": "0",
      "full_score": 1,
      "fill_hint": "填中文释义，关键词即可",
      "memory": {
        "en": "lunar",
        "zh": "阴历的，月亮的",
        "pos": "adj.",
        "phonetic": "['luːnə]",
        "pattern": "en2zh",
        "unit_tag": "【B1U8 Festivals · iWords A】",
        "lang": "zh",
        "hook": "lunar = 阴历的（先记中文，再反推拼写）",
        "fill_hint": "填中文释义，关键词即可",
        "remix_pattern": "zh2en"
      }
    },
    {
      "sort": 3,
      "type": "填空题(客观)",
      "title": "【B1U8 Festivals · iWords A】【拼写】\n团圆，相聚\n首字母 G，共 11 个字母：______",
      "options": [
        ""
      ],
      "correct_answer": "get together",
      "your_answer": "",
      "score": "0",
      "full_score": 1,
      "fill_hint": "填英文单词，小写即可；短语按原样填写",
      "memory": {
        "en": "get together",
        "zh": "团圆，相聚",
        "pos": "",
        "phonetic": "",
        "pattern": "spell",
        "unit_tag": "【B1U8 Festivals · iWords A】",
        "lang": "en",
        "hook": "逐字母：g-e-t-t-o-g-e-t-h-e-r（共 11 字母）",
        "fill_hint": "填英文单词，小写即可；短语按原样填写",
        "remix_pattern": "en2zh"
      }
    },
    {
      "sort": 4,
      "type": "填空题(客观)",
      "title": "【B1U8 Festivals · iWords A】【短语填空】\n忙着做某事\nget busy ______ sth.",
      "options": [
        ""
      ],
      "correct_answer": "doing",
      "your_answer": "",
      "score": "0",
      "full_score": 1,
      "fill_hint": "填英文单词，小写即可；短语按原样填写",
      "memory": {
        "en": "get busy doing sth.",
        "zh": "忙着做某事",
        "pos": "",
        "phonetic": "",
        "pattern": "phrase_cloze",
        "unit_tag": "【B1U8 Festivals · iWords A】",
        "lang": "en",
        "hook": "短语 get busy doing sth. ↔ 忙着做某事（整句记，再拆关键词）",
        "fill_hint": "填英文单词，小写即可；短语按原样填写",
        "remix_pattern": "en2zh"
      }
    },
    {
      "sort": 5,
      "type": "填空题(客观)",
      "title": "【B1U8 Festivals · iWords A】【中→英】\n布置，安装\n请填写英文：______",
      "options": [
        ""
      ],
      "correct_answer": "set up",
      "your_answer": "",
      "score": "0",
      "full_score": 1,
      "fill_hint": "填英文单词，小写即可；短语按原样填写",
      "memory": {
        "en": "set up",
        "zh": "布置，安装",
        "pos": "",
        "phonetic": "",
        "pattern": "zh2en",
        "unit_tag": "【B1U8 Festivals · iWords A】",
        "lang": "en",
        "hook": "「布置」→ set up（5 字母，首字母 S）",
        "fill_hint": "填英文单词，小写即可；短语按原样填写",
        "remix_pattern": "en2zh"
      }
    },
    {
      "sort": 6,
      "type": "填空题(客观)",
      "title": "【B1U8 Festivals · iWords A】【中→英】\nv. 粘贴，粘合  [peɪst]\n请填写英文：______",
      "options": [
        ""
      ],
      "correct_answer": "paste",
      "your_answer": "",
      "score": "0",
      "full_score": 1,
      "fill_hint": "填英文单词，小写即可；短语按原样填写",
      "memory": {
        "en": "paste",
        "zh": "粘贴，粘合",
        "pos": "v.",
        "phonetic": "[peɪst]",
        "pattern": "zh2en",
        "unit_tag": "【B1U8 Festivals · iWords A】",
        "lang": "en",
        "hook": "「粘贴」→ paste（5 字母，首字母 P）",
        "fill_hint": "填英文单词，小写即可；短语按原样填写",
        "remix_pattern": "en2zh"
      }
    },
    {
      "sort": 7,
      "type": "填空题(客观)",
      "title": "【B1U8 Festivals · iWords A】【英→中】\ncouplet  ['kʌplɪt]  n.\n中文释义：______",
      "options": [
        ""
      ],
      "correct_answer": "对联",
      "your_answer": "",
      "score": "0",
      "full_score": 1,
      "fill_hint": "填中文释义，关键词即可",
      "memory": {
        "en": "couplet",
        "zh": "对联，对句",
        "pos": "n.",
        "phonetic": "['kʌplɪt]",
        "pattern": "en2zh",
        "unit_tag": "【B1U8 Festivals · iWords A】",
        "lang": "zh",
        "hook": "couplet = 对联（先记中文，再反推拼写）",
        "fill_hint": "填中文释义，关键词即可",
        "remix_pattern": "zh2en"
      }
    },
    {
      "sort": 8,
      "type": "填空题(客观)",
      "title": "【B1U8 Festivals · iWords A】【拼写】\nn. 墨水\n首字母 I，共 3 个字母：______",
      "options": [
        ""
      ],
      "correct_answer": "ink",
      "your_answer": "",
      "score": "0",
      "full_score": 1,
      "fill_hint": "填英文单词，小写即可；短语按原样填写",
      "memory": {
        "en": "ink",
        "zh": "墨水",
        "pos": "n.",
        "phonetic": "[ɪŋk]",
        "pattern": "spell",
        "unit_tag": "【B1U8 Festivals · iWords A】",
        "lang": "en",
        "hook": "逐字母：i-n-k（共 3 字母）",
        "fill_hint": "填英文单词，小写即可；短语按原样填写",
        "remix_pattern": "en2zh"
      }
    },
    {
      "sort": 9,
      "type": "填空题(客观)",
      "title": "【B1U8 Festivals · iWords A】【词性】\nscroll  [skrəʊl]  卷轴\n词性（填中文，如名词、动词、形容词）：______",
      "options": [
        ""
      ],
      "correct_answer": "名词;n.;n",
      "your_answer": "",
      "score": "0",
      "full_score": 1,
      "fill_hint": "填中文词性，如：名词、动词、形容词（也可填 n. / v. / adj.）",
      "memory": {
        "en": "scroll",
        "zh": "卷轴",
        "pos": "n.",
        "phonetic": "[skrəʊl]",
        "pattern": "pos",
        "unit_tag": "【B1U8 Festivals · iWords A】",
        "pos_zh": "名词",
        "lang": "pos",
        "hook": "scroll 是名词，核心义：卷轴",
        "fill_hint": "填中文词性，如：名词、动词、形容词（也可填 n. / v. / adj.）",
        "remix_pattern": "spell"
      }
    },
    {
      "sort": 10,
      "type": "填空题(客观)",
      "title": "【B1U8 Festivals · iWords A】【英→中】\nput up  \n中文释义：______",
      "options": [
        ""
      ],
      "correct_answer": "张贴",
      "your_answer": "",
      "score": "0",
      "full_score": 1,
      "fill_hint": "填中文释义，关键词即可",
      "memory": {
        "en": "put up",
        "zh": "张贴，挂起",
        "pos": "",
        "phonetic": "",
        "pattern": "en2zh",
        "unit_tag": "【B1U8 Festivals · iWords A】",
        "lang": "zh",
        "hook": "put up = 张贴（先记中文，再反推拼写）",
        "fill_hint": "填中文释义，关键词即可",
        "remix_pattern": "zh2en"
      }
    },
    {
      "sort": 11,
      "type": "填空题(客观)",
      "title": "【B1U8 Festivals · iWords A】【中→英】\nadv. 有趣的是  ['ɪntrɪstɪŋli]\n请填写英文：______",
      "options": [
        ""
      ],
      "correct_answer": "interestingly",
      "your_answer": "",
      "score": "0",
      "full_score": 1,
      "fill_hint": "填英文单词，小写即可；短语按原样填写",
      "memory": {
        "en": "interestingly",
        "zh": "有趣的是",
        "pos": "adv.",
        "phonetic": "['ɪntrɪstɪŋli]",
        "pattern": "zh2en",
        "unit_tag": "【B1U8 Festivals · iWords A】",
        "lang": "en",
        "hook": "「有趣的是」→ interestingly（13 字母，首字母 I）",
        "fill_hint": "填英文单词，小写即可；短语按原样填写",
        "remix_pattern": "en2zh"
      }
    },
    {
      "sort": 12,
      "type": "填空题(客观)",
      "title": "【B1U8 Festivals · iWords A】【短语填空】\n颠倒，倒转\nupside ______",
      "options": [
        ""
      ],
      "correct_answer": "down",
      "your_answer": "",
      "score": "0",
      "full_score": 1,
      "fill_hint": "填英文单词，小写即可；短语按原样填写",
      "memory": {
        "en": "upside down",
        "zh": "颠倒，倒转",
        "pos": "",
        "phonetic": "",
        "pattern": "phrase_cloze",
        "unit_tag": "【B1U8 Festivals · iWords A】",
        "lang": "en",
        "hook": "短语 upside down ↔ 颠倒（整句记，再拆关键词）",
        "fill_hint": "填英文单词，小写即可；短语按原样填写",
        "remix_pattern": "en2zh"
      }
    },
    {
      "sort": 13,
      "type": "填空题(客观)",
      "title": "【B1U8 Festivals · iWords A】【拼写】\nv. 颠倒，扭转\n首字母 R，共 7 个字母：______",
      "options": [
        ""
      ],
      "correct_answer": "reverse",
      "your_answer": "",
      "score": "0",
      "full_score": 1,
      "fill_hint": "填英文单词，小写即可；短语按原样填写",
      "memory": {
        "en": "reverse",
        "zh": "颠倒，扭转",
        "pos": "v.",
        "phonetic": "[rɪ'vɜːs]",
        "pattern": "spell",
        "unit_tag": "【B1U8 Festivals · iWords A】",
        "lang": "en",
        "hook": "逐字母：r-e-v-e-r-s-e（共 7 字母）",
        "fill_hint": "填英文单词，小写即可；短语按原样填写",
        "remix_pattern": "en2zh"
      }
    },
    {
      "sort": 14,
      "type": "填空题(客观)",
      "title": "【B1U8 Festivals · iWords A】【词性】\npronounce  [prə'naʊns]  发音，读音\n词性（填中文，如名词、动词、形容词）：______",
      "options": [
        ""
      ],
      "correct_answer": "动词;v.;v",
      "your_answer": "",
      "score": "0",
      "full_score": 1,
      "fill_hint": "填中文词性，如：名词、动词、形容词（也可填 n. / v. / adj.）",
      "memory": {
        "en": "pronounce",
        "zh": "发音，读音",
        "pos": "v.",
        "phonetic": "[prə'naʊns]",
        "pattern": "pos",
        "unit_tag": "【B1U8 Festivals · iWords A】",
        "pos_zh": "动词",
        "lang": "pos",
        "hook": "pronounce 是动词，核心义：发音",
        "fill_hint": "填中文词性，如：名词、动词、形容词（也可填 n. / v. / adj.）",
        "remix_pattern": "spell"
      }
    },
    {
      "sort": 15,
      "type": "填空题(客观)",
      "title": "【B1U8 Festivals · iWords A】【联想拼写】\n团圆，重聚（n.）\nreu____ 共 7 字母：______",
      "options": [
        ""
      ],
      "correct_answer": "reunion",
      "your_answer": "",
      "score": "0",
      "full_score": 1,
      "fill_hint": "填英文单词，小写即可；短语按原样填写",
      "memory": {
        "en": "reunion",
        "zh": "团圆，重聚",
        "pos": "n.",
        "phonetic": "[ˌriː'juːnjən]",
        "pattern": "assoc",
        "unit_tag": "【B1U8 Festivals · iWords A】",
        "lang": "en",
        "hook": "联想：reu____ → reunion（团圆）",
        "fill_hint": "填英文单词，小写即可；短语按原样填写",
        "remix_pattern": "en2zh"
      }
    },
    {
      "sort": 16,
      "type": "填空题(客观)",
      "title": "【B1U8 Festivals · iWords A】【中→英】\nv. 聊天  [tʃæt]\n请填写英文：______",
      "options": [
        ""
      ],
      "correct_answer": "chat",
      "your_answer": "",
      "score": "0",
      "full_score": 1,
      "fill_hint": "填英文单词，小写即可；短语按原样填写",
      "memory": {
        "en": "chat",
        "zh": "聊天",
        "pos": "v.",
        "phonetic": "[tʃæt]",
        "pattern": "zh2en",
        "unit_tag": "【B1U8 Festivals · iWords A】",
        "lang": "en",
        "hook": "「聊天」→ chat（4 字母，首字母 C）",
        "fill_hint": "填英文单词，小写即可；短语按原样填写",
        "remix_pattern": "en2zh"
      }
    },
    {
      "sort": 17,
      "type": "填空题(客观)",
      "title": "【B1U8 Festivals · iWords A】【英→中】\ngala  ['ɡɑːlə]  n.\n中文释义：______",
      "options": [
        ""
      ],
      "correct_answer": "庆典",
      "your_answer": "",
      "score": "0",
      "full_score": 1,
      "fill_hint": "填中文释义，关键词即可",
      "memory": {
        "en": "gala",
        "zh": "庆典，盛会",
        "pos": "n.",
        "phonetic": "['ɡɑːlə]",
        "pattern": "en2zh",
        "unit_tag": "【B1U8 Festivals · iWords A】",
        "lang": "zh",
        "hook": "gala = 庆典（先记中文，再反推拼写）",
        "fill_hint": "填中文释义，关键词即可",
        "remix_pattern": "zh2en"
      }
    },
    {
      "sort": 18,
      "type": "填空题(客观)",
      "title": "【B1U8 Festivals · iWords A】【拼写】\nadj. 收视率最高的，最受关注的\n首字母 M，共 12 个字母：______",
      "options": [
        ""
      ],
      "correct_answer": "most-watched",
      "your_answer": "",
      "score": "0",
      "full_score": 1,
      "fill_hint": "填英文单词，小写即可；短语按原样填写",
      "memory": {
        "en": "most-watched",
        "zh": "收视率最高的，最受关注的",
        "pos": "adj.",
        "phonetic": "[məʊst wɒtʃt]",
        "pattern": "spell",
        "unit_tag": "【B1U8 Festivals · iWords A】",
        "lang": "en",
        "hook": "逐字母：m-o-s-t---w-a-t-c-h-e-d（共 12 字母）",
        "fill_hint": "填英文单词，小写即可；短语按原样填写",
        "remix_pattern": "en2zh"
      }
    },
    {
      "sort": 19,
      "type": "填空题(客观)",
      "title": "【B1U8 Festivals · iWords A】【拼写】\n该是做某事的时候了。\n首字母 I，共 20 个字母：______",
      "options": [
        ""
      ],
      "correct_answer": "It is high time to do sth.",
      "your_answer": "",
      "score": "0",
      "full_score": 1,
      "fill_hint": "填英文单词，小写即可；短语按原样填写",
      "memory": {
        "en": "It is high time to do sth.",
        "zh": "该是做某事的时候了。",
        "pos": "",
        "phonetic": "",
        "pattern": "spell",
        "unit_tag": "【B1U8 Festivals · iWords A】",
        "lang": "en",
        "hook": "逐字母：I-t-i-s-h-i-g-h-t-i-m-e-t-o-d-o-s-t-h-.（共 20 字母）",
        "fill_hint": "填英文单词，小写即可；短语按原样填写",
        "remix_pattern": "en2zh"
      }
    },
    {
      "sort": 20,
      "type": "填空题(客观)",
      "title": "【B1U8 Festivals · iWords A】【联想拼写】\n问候（n.）\ngre_____ 共 8 字母：______",
      "options": [
        ""
      ],
      "correct_answer": "greeting",
      "your_answer": "",
      "score": "0",
      "full_score": 1,
      "fill_hint": "填英文单词，小写即可；短语按原样填写",
      "memory": {
        "en": "greeting",
        "zh": "问候",
        "pos": "n.",
        "phonetic": "['ɡriːtɪŋ]",
        "pattern": "assoc",
        "unit_tag": "【B1U8 Festivals · iWords A】",
        "lang": "en",
        "hook": "联想：gre_____ → greeting（问候）",
        "fill_hint": "填英文单词，小写即可；短语按原样填写",
        "remix_pattern": "en2zh"
      }
    },
    {
      "sort": 21,
      "type": "填空题(客观)",
      "title": "【B1U8 Festivals · iWords A】【中→英】\nn. 应用程序（application）\n请填写英文：______",
      "options": [
        ""
      ],
      "correct_answer": "app",
      "your_answer": "",
      "score": "0",
      "full_score": 1,
      "fill_hint": "填英文单词，小写即可；短语按原样填写",
      "memory": {
        "en": "app",
        "zh": "应用程序（application）",
        "pos": "n.",
        "phonetic": "",
        "pattern": "zh2en",
        "unit_tag": "【B1U8 Festivals · iWords A】",
        "lang": "en",
        "hook": "「应用程序（application）」→ app（3 字母，首字母 A）",
        "fill_hint": "填英文单词，小写即可；短语按原样填写",
        "remix_pattern": "en2zh"
      }
    },
    {
      "sort": 22,
      "type": "填空题(客观)",
      "title": "【B1U8 Festivals · iWords A】【英→中】\nsocial app  \n中文释义：______",
      "options": [
        ""
      ],
      "correct_answer": "社交软件",
      "your_answer": "",
      "score": "0",
      "full_score": 1,
      "fill_hint": "填中文释义，关键词即可",
      "memory": {
        "en": "social app",
        "zh": "社交软件",
        "pos": "",
        "phonetic": "",
        "pattern": "en2zh",
        "unit_tag": "【B1U8 Festivals · iWords A】",
        "lang": "zh",
        "hook": "social app = 社交软件（先记中文，再反推拼写）",
        "fill_hint": "填中文释义，关键词即可",
        "remix_pattern": "zh2en"
      }
    },
    {
      "sort": 23,
      "type": "填空题(客观)",
      "title": "【B1U8 Festivals · iWords A】【拼写】\nn. 风俗，习俗\n首字母 C，共 6 个字母：______",
      "options": [
        ""
      ],
      "correct_answer": "custom",
      "your_answer": "",
      "score": "0",
      "full_score": 1,
      "fill_hint": "填英文单词，小写即可；短语按原样填写",
      "memory": {
        "en": "custom",
        "zh": "风俗，习俗",
        "pos": "n.",
        "phonetic": "['kʌstəm]",
        "pattern": "spell",
        "unit_tag": "【B1U8 Festivals · iWords A】",
        "lang": "en",
        "hook": "逐字母：c-u-s-t-o-m（共 6 字母）",
        "fill_hint": "填英文单词，小写即可；短语按原样填写",
        "remix_pattern": "en2zh"
      }
    },
    {
      "sort": 24,
      "type": "填空题(客观)",
      "title": "【B1U8 Festivals · iWords A】【短语填空】\n不睡，熬夜\nstay ______",
      "options": [
        ""
      ],
      "correct_answer": "up",
      "your_answer": "",
      "score": "0",
      "full_score": 1,
      "fill_hint": "填英文单词，小写即可；短语按原样填写",
      "memory": {
        "en": "stay up",
        "zh": "不睡，熬夜",
        "pos": "",
        "phonetic": "",
        "pattern": "phrase_cloze",
        "unit_tag": "【B1U8 Festivals · iWords A】",
        "lang": "en",
        "hook": "短语 stay up ↔ 不睡（整句记，再拆关键词）",
        "fill_hint": "填英文单词，小写即可；短语按原样填写",
        "remix_pattern": "en2zh"
      }
    },
    {
      "sort": 25,
      "type": "填空题(客观)",
      "title": "【B1U8 Festivals · iWords A】【中→英】\n守岁，迎新\n请填写英文：______",
      "options": [
        ""
      ],
      "correct_answer": "see the new year in",
      "your_answer": "",
      "score": "0",
      "full_score": 1,
      "fill_hint": "填英文单词，小写即可；短语按原样填写",
      "memory": {
        "en": "see the new year in",
        "zh": "守岁，迎新",
        "pos": "",
        "phonetic": "",
        "pattern": "zh2en",
        "unit_tag": "【B1U8 Festivals · iWords A】",
        "lang": "en",
        "hook": "「守岁」→ see the new year in（15 字母，首字母 S）",
        "fill_hint": "填英文单词，小写即可；短语按原样填写",
        "remix_pattern": "en2zh"
      }
    },
    {
      "sort": 26,
      "type": "填空题(客观)",
      "title": "【B1U8 Festivals · iWords A】【英→中】\ndress up  \n中文释义：______",
      "options": [
        ""
      ],
      "correct_answer": "盛装穿戴",
      "your_answer": "",
      "score": "0",
      "full_score": 1,
      "fill_hint": "填中文释义，关键词即可",
      "memory": {
        "en": "dress up",
        "zh": "盛装穿戴",
        "pos": "",
        "phonetic": "",
        "pattern": "en2zh",
        "unit_tag": "【B1U8 Festivals · iWords A】",
        "lang": "zh",
        "hook": "dress up = 盛装穿戴（先记中文，再反推拼写）",
        "fill_hint": "填中文释义，关键词即可",
        "remix_pattern": "zh2en"
      }
    },
    {
      "sort": 27,
      "type": "填空题(客观)",
      "title": "【B1U8 Festivals · iWords A】【英→中】\ndumpling  ['dʌmplɪŋ]  n.\n中文释义：______",
      "options": [
        ""
      ],
      "correct_answer": "饺子",
      "your_answer": "",
      "score": "0",
      "full_score": 1,
      "fill_hint": "填中文释义，关键词即可",
      "memory": {
        "en": "dumpling",
        "zh": "饺子",
        "pos": "n.",
        "phonetic": "['dʌmplɪŋ]",
        "pattern": "en2zh",
        "unit_tag": "【B1U8 Festivals · iWords A】",
        "lang": "zh",
        "hook": "dumpling = 饺子（先记中文，再反推拼写）",
        "fill_hint": "填中文释义，关键词即可",
        "remix_pattern": "zh2en"
      }
    },
    {
      "sort": 28,
      "type": "填空题(客观)",
      "title": "【B1U8 Festivals · iWords A】【短语填空】\n米糕\nrice ______",
      "options": [
        ""
      ],
      "correct_answer": "cake",
      "your_answer": "",
      "score": "0",
      "full_score": 1,
      "fill_hint": "填英文单词，小写即可；短语按原样填写",
      "memory": {
        "en": "rice cake",
        "zh": "米糕",
        "pos": "",
        "phonetic": "",
        "pattern": "phrase_cloze",
        "unit_tag": "【B1U8 Festivals · iWords A】",
        "lang": "en",
        "hook": "短语 rice cake ↔ 米糕（整句记，再拆关键词）",
        "fill_hint": "填英文单词，小写即可；短语按原样填写",
        "remix_pattern": "en2zh"
      }
    },
    {
      "sort": 29,
      "type": "填空题(客观)",
      "title": "【B1U8 Festivals · iWords A】【词性】\npacket  ['pækɪt]  小包装袋，小包\n词性（填中文，如名词、动词、形容词）：______",
      "options": [
        ""
      ],
      "correct_answer": "名词;n.;n",
      "your_answer": "",
      "score": "0",
      "full_score": 1,
      "fill_hint": "填中文词性，如：名词、动词、形容词（也可填 n. / v. / adj.）",
      "memory": {
        "en": "packet",
        "zh": "小包装袋，小包",
        "pos": "n.",
        "phonetic": "['pækɪt]",
        "pattern": "pos",
        "unit_tag": "【B1U8 Festivals · iWords A】",
        "pos_zh": "名词",
        "lang": "pos",
        "hook": "packet 是名词，核心义：小包装袋",
        "fill_hint": "填中文词性，如：名词、动词、形容词（也可填 n. / v. / adj.）",
        "remix_pattern": "spell"
      }
    },
    {
      "sort": 30,
      "type": "填空题(客观)",
      "title": "【B1U8 Festivals · iWords A】【英→中】\nset off  \n中文释义：______",
      "options": [
        ""
      ],
      "correct_answer": "施放",
      "your_answer": "",
      "score": "0",
      "full_score": 1,
      "fill_hint": "填中文释义，关键词即可",
      "memory": {
        "en": "set off",
        "zh": "施放，点燃",
        "pos": "",
        "phonetic": "",
        "pattern": "en2zh",
        "unit_tag": "【B1U8 Festivals · iWords A】",
        "lang": "zh",
        "hook": "set off = 施放（先记中文，再反推拼写）",
        "fill_hint": "填中文释义，关键词即可",
        "remix_pattern": "zh2en"
      }
    },
    {
      "sort": 31,
      "type": "填空题(客观)",
      "title": "【B1U8 Festivals · iWords A】【中→英】\nn. 烟花  ['faɪəwɜːk]\n请填写英文：______",
      "options": [
        ""
      ],
      "correct_answer": "firework",
      "your_answer": "",
      "score": "0",
      "full_score": 1,
      "fill_hint": "填英文单词，小写即可；短语按原样填写",
      "memory": {
        "en": "firework",
        "zh": "烟花",
        "pos": "n.",
        "phonetic": "['faɪəwɜːk]",
        "pattern": "zh2en",
        "unit_tag": "【B1U8 Festivals · iWords A】",
        "lang": "en",
        "hook": "「烟花」→ firework（8 字母，首字母 F）",
        "fill_hint": "填英文单词，小写即可；短语按原样填写",
        "remix_pattern": "en2zh"
      }
    },
    {
      "sort": 32,
      "type": "填空题(客观)",
      "title": "【B1U8 Festivals · iWords A】【英→中】\ntypical  ['tɪpɪkl]  adj.\n中文释义：______",
      "options": [
        ""
      ],
      "correct_answer": "典型的",
      "your_answer": "",
      "score": "0",
      "full_score": 1,
      "fill_hint": "填中文释义，关键词即可",
      "memory": {
        "en": "typical",
        "zh": "典型的",
        "pos": "adj.",
        "phonetic": "['tɪpɪkl]",
        "pattern": "en2zh",
        "unit_tag": "【B1U8 Festivals · iWords A】",
        "lang": "zh",
        "hook": "typical = 典型的（先记中文，再反推拼写）",
        "fill_hint": "填中文释义，关键词即可",
        "remix_pattern": "zh2en"
      }
    },
    {
      "sort": 33,
      "type": "填空题(客观)",
      "title": "【B1U8 Festivals · iWords A】【拼写】\nn. 爆竹\n首字母 F，共 11 个字母：______",
      "options": [
        ""
      ],
      "correct_answer": "firecracker",
      "your_answer": "",
      "score": "0",
      "full_score": 1,
      "fill_hint": "填英文单词，小写即可；短语按原样填写",
      "memory": {
        "en": "firecracker",
        "zh": "爆竹",
        "pos": "n.",
        "phonetic": "['faɪəkrækə]",
        "pattern": "spell",
        "unit_tag": "【B1U8 Festivals · iWords A】",
        "lang": "en",
        "hook": "逐字母：f-i-r-e-c-r-a-c-k-e-r（共 11 字母）",
        "fill_hint": "填英文单词，小写即可；短语按原样填写",
        "remix_pattern": "en2zh"
      }
    },
    {
      "sort": 34,
      "type": "填空题(客观)",
      "title": "【B1U8 Festivals · iWords A】【词性】\nban  [bæn]  禁令\n词性（填中文，如名词、动词、形容词）：______",
      "options": [
        ""
      ],
      "correct_answer": "名词;n.;n",
      "your_answer": "",
      "score": "0",
      "full_score": 1,
      "fill_hint": "填中文词性，如：名词、动词、形容词（也可填 n. / v. / adj.）",
      "memory": {
        "en": "ban",
        "zh": "禁令",
        "pos": "n.",
        "phonetic": "[bæn]",
        "pattern": "pos",
        "unit_tag": "【B1U8 Festivals · iWords A】",
        "pos_zh": "名词",
        "lang": "pos",
        "hook": "ban 是名词，核心义：禁令",
        "fill_hint": "填中文词性，如：名词、动词、形容词（也可填 n. / v. / adj.）",
        "remix_pattern": "spell"
      }
    },
    {
      "sort": 35,
      "type": "填空题(客观)",
      "title": "【B1U8 Festivals · iWords A】【联想拼写】\n事故（n.）\nacc_____ 共 8 字母：______",
      "options": [
        ""
      ],
      "correct_answer": "accident",
      "your_answer": "",
      "score": "0",
      "full_score": 1,
      "fill_hint": "填英文单词，小写即可；短语按原样填写",
      "memory": {
        "en": "accident",
        "zh": "事故",
        "pos": "n.",
        "phonetic": "['æksɪdənt]",
        "pattern": "assoc",
        "unit_tag": "【B1U8 Festivals · iWords A】",
        "lang": "en",
        "hook": "联想：acc_____ → accident（事故）",
        "fill_hint": "填英文单词，小写即可；短语按原样填写",
        "remix_pattern": "en2zh"
      }
    },
    {
      "sort": 36,
      "type": "填空题(客观)",
      "title": "【B1U8 Festivals · iWords A】【中→英】\nn. 威胁  [θret]\n请填写英文：______",
      "options": [
        ""
      ],
      "correct_answer": "threat",
      "your_answer": "",
      "score": "0",
      "full_score": 1,
      "fill_hint": "填英文单词，小写即可；短语按原样填写",
      "memory": {
        "en": "threat",
        "zh": "威胁",
        "pos": "n.",
        "phonetic": "[θret]",
        "pattern": "zh2en",
        "unit_tag": "【B1U8 Festivals · iWords A】",
        "lang": "en",
        "hook": "「威胁」→ threat（6 字母，首字母 T）",
        "fill_hint": "填英文单词，小写即可；短语按原样填写",
        "remix_pattern": "en2zh"
      }
    },
    {
      "sort": 37,
      "type": "填空题(客观)",
      "title": "【B1U8 Festivals · iWords A】【英→中】\nquality  ['kwɒlɪti]  n.\n中文释义：______",
      "options": [
        ""
      ],
      "correct_answer": "质量",
      "your_answer": "",
      "score": "0",
      "full_score": 1,
      "fill_hint": "填中文释义，关键词即可",
      "memory": {
        "en": "quality",
        "zh": "质量",
        "pos": "n.",
        "phonetic": "['kwɒlɪti]",
        "pattern": "en2zh",
        "unit_tag": "【B1U8 Festivals · iWords A】",
        "lang": "zh",
        "hook": "quality = 质量（先记中文，再反推拼写）",
        "fill_hint": "填中文释义，关键词即可",
        "remix_pattern": "zh2en"
      }
    },
    {
      "sort": 38,
      "type": "填空题(客观)",
      "title": "【B1U8 Festivals · iWords A】【英→中】\nlion dancing  \n中文释义：______",
      "options": [
        ""
      ],
      "correct_answer": "舞狮子",
      "your_answer": "",
      "score": "0",
      "full_score": 1,
      "fill_hint": "填中文释义，关键词即可",
      "memory": {
        "en": "lion dancing",
        "zh": "舞狮子",
        "pos": "",
        "phonetic": "",
        "pattern": "en2zh",
        "unit_tag": "【B1U8 Festivals · iWords A】",
        "lang": "zh",
        "hook": "lion dancing = 舞狮子（先记中文，再反推拼写）",
        "fill_hint": "填中文释义，关键词即可",
        "remix_pattern": "zh2en"
      }
    },
    {
      "sort": 39,
      "type": "填空题(客观)",
      "title": "【B1U8 Festivals · iWords A】【词性】\ndragon  ['dræɡən]  龙\n词性（填中文，如名词、动词、形容词）：______",
      "options": [
        ""
      ],
      "correct_answer": "名词;n.;n",
      "your_answer": "",
      "score": "0",
      "full_score": 1,
      "fill_hint": "填中文词性，如：名词、动词、形容词（也可填 n. / v. / adj.）",
      "memory": {
        "en": "dragon",
        "zh": "龙",
        "pos": "n.",
        "phonetic": "['dræɡən]",
        "pattern": "pos",
        "unit_tag": "【B1U8 Festivals · iWords A】",
        "pos_zh": "名词",
        "lang": "pos",
        "hook": "dragon 是名词，核心义：龙",
        "fill_hint": "填中文词性，如：名词、动词、形容词（也可填 n. / v. / adj.）",
        "remix_pattern": "spell"
      }
    },
    {
      "sort": 40,
      "type": "填空题(客观)",
      "title": "【B1U8 Festivals · iWords A】【短语填空】\n舞龙\ndragon ______",
      "options": [
        ""
      ],
      "correct_answer": "dancing",
      "your_answer": "",
      "score": "0",
      "full_score": 1,
      "fill_hint": "填英文单词，小写即可；短语按原样填写",
      "memory": {
        "en": "dragon dancing",
        "zh": "舞龙",
        "pos": "",
        "phonetic": "",
        "pattern": "phrase_cloze",
        "unit_tag": "【B1U8 Festivals · iWords A】",
        "lang": "en",
        "hook": "短语 dragon dancing ↔ 舞龙（整句记，再拆关键词）",
        "fill_hint": "填英文单词，小写即可；短语按原样填写",
        "remix_pattern": "en2zh"
      }
    },
    {
      "sort": 41,
      "type": "填空题(客观)",
      "title": "【B1U8 Festivals · iWords A】【中→英】\n庙会\n请填写英文：______",
      "options": [
        ""
      ],
      "correct_answer": "temple fair",
      "your_answer": "",
      "score": "0",
      "full_score": 1,
      "fill_hint": "填英文单词，小写即可；短语按原样填写",
      "memory": {
        "en": "temple fair",
        "zh": "庙会",
        "pos": "",
        "phonetic": "",
        "pattern": "zh2en",
        "unit_tag": "【B1U8 Festivals · iWords A】",
        "lang": "en",
        "hook": "「庙会」→ temple fair（10 字母，首字母 T）",
        "fill_hint": "填英文单词，小写即可；短语按原样填写",
        "remix_pattern": "en2zh"
      }
    },
    {
      "sort": 42,
      "type": "填空题(客观)",
      "title": "【B1U8 Festivals · iWords A】【英→中】\nlantern  ['læntən]  n.\n中文释义：______",
      "options": [
        ""
      ],
      "correct_answer": "灯笼",
      "your_answer": "",
      "score": "0",
      "full_score": 1,
      "fill_hint": "填中文释义，关键词即可",
      "memory": {
        "en": "lantern",
        "zh": "灯笼",
        "pos": "n.",
        "phonetic": "['læntən]",
        "pattern": "en2zh",
        "unit_tag": "【B1U8 Festivals · iWords A】",
        "lang": "zh",
        "hook": "lantern = 灯笼（先记中文，再反推拼写）",
        "fill_hint": "填中文释义，关键词即可",
        "remix_pattern": "zh2en"
      }
    },
    {
      "sort": 43,
      "type": "填空题(客观)",
      "title": "【B1U8 Festivals · iWords A】【拼写】\nadv. 正式地，官方地\n首字母 O，共 10 个字母：______",
      "options": [
        ""
      ],
      "correct_answer": "officially",
      "your_answer": "",
      "score": "0",
      "full_score": 1,
      "fill_hint": "填英文单词，小写即可；短语按原样填写",
      "memory": {
        "en": "officially",
        "zh": "正式地，官方地",
        "pos": "adv.",
        "phonetic": "[ə'fɪʃəli]",
        "pattern": "spell",
        "unit_tag": "【B1U8 Festivals · iWords A】",
        "lang": "en",
        "hook": "逐字母：o-f-f-i-c-i-a-l-l-y（共 10 字母）",
        "fill_hint": "填英文单词，小写即可；短语按原样填写",
        "remix_pattern": "en2zh"
      }
    },
    {
      "sort": 44,
      "type": "填空题(客观)",
      "title": "【B1U8 Festivals · iWords B】【词性】\nChristmas  ['krɪsməs]  圣诞节\n词性（填中文，如名词、动词、形容词）：______",
      "options": [
        ""
      ],
      "correct_answer": "名词;n.;n",
      "your_answer": "",
      "score": "0",
      "full_score": 1,
      "fill_hint": "填中文词性，如：名词、动词、形容词（也可填 n. / v. / adj.）",
      "memory": {
        "en": "Christmas",
        "zh": "圣诞节",
        "pos": "n.",
        "phonetic": "['krɪsməs]",
        "pattern": "pos",
        "unit_tag": "【B1U8 Festivals · iWords B】",
        "pos_zh": "名词",
        "lang": "pos",
        "hook": "Christmas 是名词，核心义：圣诞节",
        "fill_hint": "填中文词性，如：名词、动词、形容词（也可填 n. / v. / adj.）",
        "remix_pattern": "spell"
      }
    },
    {
      "sort": 45,
      "type": "填空题(客观)",
      "title": "【B1U8 Festivals · iWords B】【中→英】\n期待，盼望\n请填写英文：______",
      "options": [
        ""
      ],
      "correct_answer": "look forward to",
      "your_answer": "",
      "score": "0",
      "full_score": 1,
      "fill_hint": "填英文单词，小写即可；短语按原样填写",
      "memory": {
        "en": "look forward to",
        "zh": "期待，盼望",
        "pos": "",
        "phonetic": "",
        "pattern": "zh2en",
        "unit_tag": "【B1U8 Festivals · iWords B】",
        "lang": "en",
        "hook": "「期待」→ look forward to（13 字母，首字母 L）",
        "fill_hint": "填英文单词，小写即可；短语按原样填写",
        "remix_pattern": "en2zh"
      }
    },
    {
      "sort": 46,
      "type": "填空题(客观)",
      "title": "【B1U8 Festivals · iWords B】【中→英】\nn. 单身汉  ['bætʃələ]\n请填写英文：______",
      "options": [
        ""
      ],
      "correct_answer": "bachelor",
      "your_answer": "",
      "score": "0",
      "full_score": 1,
      "fill_hint": "填英文单词，小写即可；短语按原样填写",
      "memory": {
        "en": "bachelor",
        "zh": "单身汉",
        "pos": "n.",
        "phonetic": "['bætʃələ]",
        "pattern": "zh2en",
        "unit_tag": "【B1U8 Festivals · iWords B】",
        "lang": "en",
        "hook": "「单身汉」→ bachelor（8 字母，首字母 B）",
        "fill_hint": "填英文单词，小写即可；短语按原样填写",
        "remix_pattern": "en2zh"
      }
    },
    {
      "sort": 47,
      "type": "填空题(客观)",
      "title": "【B1U8 Festivals · iWords B】【拼写】\n城外，郊区\n首字母 O，共 9 个字母：______",
      "options": [
        ""
      ],
      "correct_answer": "out of town",
      "your_answer": "",
      "score": "0",
      "full_score": 1,
      "fill_hint": "填英文单词，小写即可；短语按原样填写",
      "memory": {
        "en": "out of town",
        "zh": "城外，郊区",
        "pos": "",
        "phonetic": "",
        "pattern": "spell",
        "unit_tag": "【B1U8 Festivals · iWords B】",
        "lang": "en",
        "hook": "逐字母：o-u-t-o-f-t-o-w-n（共 9 字母）",
        "fill_hint": "填英文单词，小写即可；短语按原样填写",
        "remix_pattern": "en2zh"
      }
    },
    {
      "sort": 48,
      "type": "填空题(客观)",
      "title": "【B1U8 Festivals · iWords B】【拼写】\nn. 智能手机\n首字母 S，共 10 个字母：______",
      "options": [
        ""
      ],
      "correct_answer": "smartphone",
      "your_answer": "",
      "score": "0",
      "full_score": 1,
      "fill_hint": "填英文单词，小写即可；短语按原样填写",
      "memory": {
        "en": "smartphone",
        "zh": "智能手机",
        "pos": "n.",
        "phonetic": "",
        "pattern": "spell",
        "unit_tag": "【B1U8 Festivals · iWords B】",
        "lang": "en",
        "hook": "逐字母：s-m-a-r-t-p-h-o-n-e（共 10 字母）",
        "fill_hint": "填英文单词，小写即可；短语按原样填写",
        "remix_pattern": "en2zh"
      }
    },
    {
      "sort": 49,
      "type": "填空题(客观)",
      "title": "【B1U8 Festivals · iWords B】【词性】\nWi-Fi  （wireless fidelity 的缩写）无线网络\n词性（填中文，如名词、动词、形容词）：______",
      "options": [
        ""
      ],
      "correct_answer": "名词;n.;n",
      "your_answer": "",
      "score": "0",
      "full_score": 1,
      "fill_hint": "填中文词性，如：名词、动词、形容词（也可填 n. / v. / adj.）",
      "memory": {
        "en": "Wi-Fi",
        "zh": "（wireless fidelity 的缩写）无线网络",
        "pos": "n.",
        "phonetic": "",
        "pattern": "pos",
        "unit_tag": "【B1U8 Festivals · iWords B】",
        "pos_zh": "名词",
        "lang": "pos",
        "hook": "Wi-Fi 是名词，核心义：（wireless fidelity 的缩写）无线网络",
        "fill_hint": "填中文词性，如：名词、动词、形容词（也可填 n. / v. / adj.）",
        "remix_pattern": "spell"
      }
    },
    {
      "sort": 50,
      "type": "填空题(客观)",
      "title": "【B1U8 Festivals · iWords B】【联想拼写】\n缺乏，没有（v.）\nlac_ 共 4 字母：______",
      "options": [
        ""
      ],
      "correct_answer": "lack",
      "your_answer": "",
      "score": "0",
      "full_score": 1,
      "fill_hint": "填英文单词，小写即可；短语按原样填写",
      "memory": {
        "en": "lack",
        "zh": "缺乏，没有",
        "pos": "v.",
        "phonetic": "[læk]",
        "pattern": "assoc",
        "unit_tag": "【B1U8 Festivals · iWords B】",
        "lang": "en",
        "hook": "联想：lac_ → lack（缺乏）",
        "fill_hint": "填英文单词，小写即可；短语按原样填写",
        "remix_pattern": "en2zh"
      }
    },
    {
      "sort": 51,
      "type": "填空题(客观)",
      "title": "【B1U8 Festivals · iWords B】【拼写】\n保有（工作等）\n首字母 H，共 8 个字母：______",
      "options": [
        ""
      ],
      "correct_answer": "hold down",
      "your_answer": "",
      "score": "0",
      "full_score": 1,
      "fill_hint": "填英文单词，小写即可；短语按原样填写",
      "memory": {
        "en": "hold down",
        "zh": "保有（工作等）",
        "pos": "",
        "phonetic": "",
        "pattern": "spell",
        "unit_tag": "【B1U8 Festivals · iWords B】",
        "lang": "en",
        "hook": "逐字母：h-o-l-d-d-o-w-n（共 8 字母）",
        "fill_hint": "填英文单词，小写即可；短语按原样填写",
        "remix_pattern": "en2zh"
      }
    },
    {
      "sort": 52,
      "type": "填空题(客观)",
      "title": "【B1U8 Festivals · iWords B】【英→中】\nintend  [ɪn'tend]  v.\n中文释义：______",
      "options": [
        ""
      ],
      "correct_answer": "想要",
      "your_answer": "",
      "score": "0",
      "full_score": 1,
      "fill_hint": "填中文释义，关键词即可",
      "memory": {
        "en": "intend",
        "zh": "想要，打算",
        "pos": "v.",
        "phonetic": "[ɪn'tend]",
        "pattern": "en2zh",
        "unit_tag": "【B1U8 Festivals · iWords B】",
        "lang": "zh",
        "hook": "intend = 想要（先记中文，再反推拼写）",
        "fill_hint": "填中文释义，关键词即可",
        "remix_pattern": "zh2en"
      }
    },
    {
      "sort": 53,
      "type": "填空题(客观)",
      "title": "【B1U8 Festivals · iWords B】【拼写】\nn. 亲戚\n首字母 R，共 8 个字母：______",
      "options": [
        ""
      ],
      "correct_answer": "relative",
      "your_answer": "",
      "score": "0",
      "full_score": 1,
      "fill_hint": "填英文单词，小写即可；短语按原样填写",
      "memory": {
        "en": "relative",
        "zh": "亲戚",
        "pos": "n.",
        "phonetic": "['relətɪv]",
        "pattern": "spell",
        "unit_tag": "【B1U8 Festivals · iWords B】",
        "lang": "en",
        "hook": "逐字母：r-e-l-a-t-i-v-e（共 8 字母）",
        "fill_hint": "填英文单词，小写即可；短语按原样填写",
        "remix_pattern": "en2zh"
      }
    },
    {
      "sort": 54,
      "type": "填空题(客观)",
      "title": "【B1U8 Festivals · iWords B】【英→中】\ndraw near  \n中文释义：______",
      "options": [
        ""
      ],
      "correct_answer": "临近",
      "your_answer": "",
      "score": "0",
      "full_score": 1,
      "fill_hint": "填中文释义，关键词即可",
      "memory": {
        "en": "draw near",
        "zh": "临近，走近",
        "pos": "",
        "phonetic": "",
        "pattern": "en2zh",
        "unit_tag": "【B1U8 Festivals · iWords B】",
        "lang": "zh",
        "hook": "draw near = 临近（先记中文，再反推拼写）",
        "fill_hint": "填中文释义，关键词即可",
        "remix_pattern": "zh2en"
      }
    },
    {
      "sort": 55,
      "type": "填空题(客观)",
      "title": "【B1U8 Festivals · iWords B】【联想拼写】\n认识到，了解（v.）\nrea____ 共 7 字母：______",
      "options": [
        ""
      ],
      "correct_answer": "realize",
      "your_answer": "",
      "score": "0",
      "full_score": 1,
      "fill_hint": "填英文单词，小写即可；短语按原样填写",
      "memory": {
        "en": "realize",
        "zh": "认识到，了解",
        "pos": "v.",
        "phonetic": "['rɪəlaɪz]",
        "pattern": "assoc",
        "unit_tag": "【B1U8 Festivals · iWords B】",
        "lang": "en",
        "hook": "联想：rea____ → realize（认识到）",
        "fill_hint": "填英文单词，小写即可；短语按原样填写",
        "remix_pattern": "en2zh"
      }
    },
    {
      "sort": 56,
      "type": "填空题(客观)",
      "title": "【B1U8 Festivals · iWords B】【中→英】\nn. 前夕，前夜  [iːv]\n请填写英文：______",
      "options": [
        ""
      ],
      "correct_answer": "eve",
      "your_answer": "",
      "score": "0",
      "full_score": 1,
      "fill_hint": "填英文单词，小写即可；短语按原样填写",
      "memory": {
        "en": "eve",
        "zh": "前夕，前夜",
        "pos": "n.",
        "phonetic": "[iːv]",
        "pattern": "zh2en",
        "unit_tag": "【B1U8 Festivals · iWords B】",
        "lang": "en",
        "hook": "「前夕」→ eve（3 字母，首字母 E）",
        "fill_hint": "填英文单词，小写即可；短语按原样填写",
        "remix_pattern": "en2zh"
      }
    },
    {
      "sort": 57,
      "type": "填空题(客观)",
      "title": "【B1U8 Festivals · iWords B】【英→中】\nremove  [rɪ'muːv]  v.\n中文释义：______",
      "options": [
        ""
      ],
      "correct_answer": "移动；去掉",
      "your_answer": "",
      "score": "0",
      "full_score": 1,
      "fill_hint": "填中文释义，关键词即可",
      "memory": {
        "en": "remove",
        "zh": "移动；去掉",
        "pos": "v.",
        "phonetic": "[rɪ'muːv]",
        "pattern": "en2zh",
        "unit_tag": "【B1U8 Festivals · iWords B】",
        "lang": "zh",
        "hook": "remove = 移动（先记中文，再反推拼写）",
        "fill_hint": "填中文释义，关键词即可",
        "remix_pattern": "zh2en"
      }
    },
    {
      "sort": 58,
      "type": "填空题(客观)",
      "title": "【B1U8 Festivals · iWords B】【英→中】\nremove ... from  \n中文释义：______",
      "options": [
        ""
      ],
      "correct_answer": "把……移走",
      "your_answer": "",
      "score": "0",
      "full_score": 1,
      "fill_hint": "填中文释义，关键词即可",
      "memory": {
        "en": "remove ... from",
        "zh": "把……移走，除掉",
        "pos": "",
        "phonetic": "",
        "pattern": "en2zh",
        "unit_tag": "【B1U8 Festivals · iWords B】",
        "lang": "zh",
        "hook": "remove ... from = 把……移走（先记中文，再反推拼写）",
        "fill_hint": "填中文释义，关键词即可",
        "remix_pattern": "zh2en"
      }
    },
    {
      "sort": 59,
      "type": "填空题(客观)",
      "title": "【B1U8 Festivals · iWords B】【词性】\ndecoration  [ˌdekə'reɪʃn]  装饰，装饰品\n词性（填中文，如名词、动词、形容词）：______",
      "options": [
        ""
      ],
      "correct_answer": "名词;n.;n",
      "your_answer": "",
      "score": "0",
      "full_score": 1,
      "fill_hint": "填中文词性，如：名词、动词、形容词（也可填 n. / v. / adj.）",
      "memory": {
        "en": "decoration",
        "zh": "装饰，装饰品",
        "pos": "n.",
        "phonetic": "[ˌdekə'reɪʃn]",
        "pattern": "pos",
        "unit_tag": "【B1U8 Festivals · iWords B】",
        "pos_zh": "名词",
        "lang": "pos",
        "hook": "decoration 是名词，核心义：装饰",
        "fill_hint": "填中文词性，如：名词、动词、形容词（也可填 n. / v. / adj.）",
        "remix_pattern": "spell"
      }
    },
    {
      "sort": 60,
      "type": "填空题(客观)",
      "title": "【B1U8 Festivals · iWords B】【联想拼写】\n把……打包（v.）\npac_ 共 4 字母：______",
      "options": [
        ""
      ],
      "correct_answer": "pack",
      "your_answer": "",
      "score": "0",
      "full_score": 1,
      "fill_hint": "填英文单词，小写即可；短语按原样填写",
      "memory": {
        "en": "pack",
        "zh": "把……打包",
        "pos": "v.",
        "phonetic": "[pæk]",
        "pattern": "assoc",
        "unit_tag": "【B1U8 Festivals · iWords B】",
        "lang": "en",
        "hook": "联想：pac_ → pack（把……打包）",
        "fill_hint": "填英文单词，小写即可；短语按原样填写",
        "remix_pattern": "en2zh"
      }
    },
    {
      "sort": 61,
      "type": "填空题(客观)",
      "title": "【B1U8 Festivals · iWords B】【中→英】\n打包\n请填写英文：______",
      "options": [
        ""
      ],
      "correct_answer": "pack up",
      "your_answer": "",
      "score": "0",
      "full_score": 1,
      "fill_hint": "填英文单词，小写即可；短语按原样填写",
      "memory": {
        "en": "pack up",
        "zh": "打包",
        "pos": "",
        "phonetic": "",
        "pattern": "zh2en",
        "unit_tag": "【B1U8 Festivals · iWords B】",
        "lang": "en",
        "hook": "「打包」→ pack up（6 字母，首字母 P）",
        "fill_hint": "填英文单词，小写即可；短语按原样填写",
        "remix_pattern": "en2zh"
      }
    },
    {
      "sort": 62,
      "type": "填空题(客观)",
      "title": "【B1U8 Festivals · iWords B】【英→中】\nalong with  \n中文释义：______",
      "options": [
        ""
      ],
      "correct_answer": "连同……一起",
      "your_answer": "",
      "score": "0",
      "full_score": 1,
      "fill_hint": "填中文释义，关键词即可",
      "memory": {
        "en": "along with",
        "zh": "连同……一起",
        "pos": "",
        "phonetic": "",
        "pattern": "en2zh",
        "unit_tag": "【B1U8 Festivals · iWords B】",
        "lang": "zh",
        "hook": "along with = 连同……一起（先记中文，再反推拼写）",
        "fill_hint": "填中文释义，关键词即可",
        "remix_pattern": "zh2en"
      }
    },
    {
      "sort": 63,
      "type": "填空题(客观)",
      "title": "【B1U8 Festivals · iWords B】【拼写】\nn. 配料；装饰品\n首字母 T，共 8 个字母：______",
      "options": [
        ""
      ],
      "correct_answer": "trimming",
      "your_answer": "",
      "score": "0",
      "full_score": 1,
      "fill_hint": "填英文单词，小写即可；短语按原样填写",
      "memory": {
        "en": "trimming",
        "zh": "配料；装饰品",
        "pos": "n.",
        "phonetic": "['trɪmɪŋ]",
        "pattern": "spell",
        "unit_tag": "【B1U8 Festivals · iWords B】",
        "lang": "en",
        "hook": "逐字母：t-r-i-m-m-i-n-g（共 8 字母）",
        "fill_hint": "填英文单词，小写即可；短语按原样填写",
        "remix_pattern": "en2zh"
      }
    },
    {
      "sort": 64,
      "type": "填空题(客观)",
      "title": "【B1U8 Festivals · iWords B】【词性】\nturkey  ['tɜːki]  火鸡\n词性（填中文，如名词、动词、形容词）：______",
      "options": [
        ""
      ],
      "correct_answer": "名词;n.;n",
      "your_answer": "",
      "score": "0",
      "full_score": 1,
      "fill_hint": "填中文词性，如：名词、动词、形容词（也可填 n. / v. / adj.）",
      "memory": {
        "en": "turkey",
        "zh": "火鸡",
        "pos": "n.",
        "phonetic": "['tɜːki]",
        "pattern": "pos",
        "unit_tag": "【B1U8 Festivals · iWords B】",
        "pos_zh": "名词",
        "lang": "pos",
        "hook": "turkey 是名词，核心义：火鸡",
        "fill_hint": "填中文词性，如：名词、动词、形容词（也可填 n. / v. / adj.）",
        "remix_pattern": "spell"
      }
    },
    {
      "sort": 65,
      "type": "填空题(客观)",
      "title": "【B1U8 Festivals · iWords B】【联想拼写】\n破晓，（天）初亮（v.）\ndaw_ 共 4 字母：______",
      "options": [
        ""
      ],
      "correct_answer": "dawn",
      "your_answer": "",
      "score": "0",
      "full_score": 1,
      "fill_hint": "填英文单词，小写即可；短语按原样填写",
      "memory": {
        "en": "dawn",
        "zh": "破晓，（天）初亮",
        "pos": "v.",
        "phonetic": "[dɔːn]",
        "pattern": "assoc",
        "unit_tag": "【B1U8 Festivals · iWords B】",
        "lang": "en",
        "hook": "联想：daw_ → dawn（破晓）",
        "fill_hint": "填英文单词，小写即可；短语按原样填写",
        "remix_pattern": "en2zh"
      }
    },
    {
      "sort": 66,
      "type": "填空题(客观)",
      "title": "【B1U8 Festivals · iWords B】【中→英】\nadv. 完美地，完全地  ['pɜːfɪktli]\n请填写英文：______",
      "options": [
        ""
      ],
      "correct_answer": "perfectly",
      "your_answer": "",
      "score": "0",
      "full_score": 1,
      "fill_hint": "填英文单词，小写即可；短语按原样填写",
      "memory": {
        "en": "perfectly",
        "zh": "完美地，完全地",
        "pos": "adv.",
        "phonetic": "['pɜːfɪktli]",
        "pattern": "zh2en",
        "unit_tag": "【B1U8 Festivals · iWords B】",
        "lang": "en",
        "hook": "「完美地」→ perfectly（9 字母，首字母 P）",
        "fill_hint": "填英文单词，小写即可；短语按原样填写",
        "remix_pattern": "en2zh"
      }
    },
    {
      "sort": 67,
      "type": "填空题(客观)",
      "title": "【B1U8 Festivals · iWords B】【英→中】\nbrightly  ['braɪtli]  adv.\n中文释义：______",
      "options": [
        ""
      ],
      "correct_answer": "明亮地",
      "your_answer": "",
      "score": "0",
      "full_score": 1,
      "fill_hint": "填中文释义，关键词即可",
      "memory": {
        "en": "brightly",
        "zh": "明亮地",
        "pos": "adv.",
        "phonetic": "['braɪtli]",
        "pattern": "en2zh",
        "unit_tag": "【B1U8 Festivals · iWords B】",
        "lang": "zh",
        "hook": "brightly = 明亮地（先记中文，再反推拼写）",
        "fill_hint": "填中文释义，关键词即可",
        "remix_pattern": "zh2en"
      }
    },
    {
      "sort": 68,
      "type": "填空题(客观)",
      "title": "【B1U8 Festivals · iWords B】【拼写】\nn. 覆盖的一层\n首字母 B，共 7 个字母：______",
      "options": [
        ""
      ],
      "correct_answer": "blanket",
      "your_answer": "",
      "score": "0",
      "full_score": 1,
      "fill_hint": "填英文单词，小写即可；短语按原样填写",
      "memory": {
        "en": "blanket",
        "zh": "覆盖的一层",
        "pos": "n.",
        "phonetic": "['blæŋkɪt]",
        "pattern": "spell",
        "unit_tag": "【B1U8 Festivals · iWords B】",
        "lang": "en",
        "hook": "逐字母：b-l-a-n-k-e-t（共 7 字母）",
        "fill_hint": "填英文单词，小写即可；短语按原样填写",
        "remix_pattern": "en2zh"
      }
    },
    {
      "sort": 69,
      "type": "填空题(客观)",
      "title": "【B1U8 Festivals · iWords B】【词性】\nbackseat  [bæk'siːt]  后座\n词性（填中文，如名词、动词、形容词）：______",
      "options": [
        ""
      ],
      "correct_answer": "名词;n.;n",
      "your_answer": "",
      "score": "0",
      "full_score": 1,
      "fill_hint": "填中文词性，如：名词、动词、形容词（也可填 n. / v. / adj.）",
      "memory": {
        "en": "backseat",
        "zh": "后座",
        "pos": "n.",
        "phonetic": "[bæk'siːt]",
        "pattern": "pos",
        "unit_tag": "【B1U8 Festivals · iWords B】",
        "pos_zh": "名词",
        "lang": "pos",
        "hook": "backseat 是名词，核心义：后座",
        "fill_hint": "填中文词性，如：名词、动词、形容词（也可填 n. / v. / adj.）",
        "remix_pattern": "spell"
      }
    },
    {
      "sort": 70,
      "type": "填空题(客观)",
      "title": "【B1U8 Festivals · iWords B】【联想拼写】\n默默地，静静地（adv.）\nsil_____ 共 8 字母：______",
      "options": [
        ""
      ],
      "correct_answer": "silently",
      "your_answer": "",
      "score": "0",
      "full_score": 1,
      "fill_hint": "填英文单词，小写即可；短语按原样填写",
      "memory": {
        "en": "silently",
        "zh": "默默地，静静地",
        "pos": "adv.",
        "phonetic": "['saɪləntli]",
        "pattern": "assoc",
        "unit_tag": "【B1U8 Festivals · iWords B】",
        "lang": "en",
        "hook": "联想：sil_____ → silently（默默地）",
        "fill_hint": "填英文单词，小写即可；短语按原样填写",
        "remix_pattern": "en2zh"
      }
    },
    {
      "sort": 71,
      "type": "填空题(客观)",
      "title": "【B1U8 Festivals · iWords B】【中→英】\nadj. 心烦意乱的，烦恼的  [ʌp'set]\n请填写英文：______",
      "options": [
        ""
      ],
      "correct_answer": "upset",
      "your_answer": "",
      "score": "0",
      "full_score": 1,
      "fill_hint": "填英文单词，小写即可；短语按原样填写",
      "memory": {
        "en": "upset",
        "zh": "心烦意乱的，烦恼的",
        "pos": "adj.",
        "phonetic": "[ʌp'set]",
        "pattern": "zh2en",
        "unit_tag": "【B1U8 Festivals · iWords B】",
        "lang": "en",
        "hook": "「心烦意乱的」→ upset（5 字母，首字母 U）",
        "fill_hint": "填英文单词，小写即可；短语按原样填写",
        "remix_pattern": "en2zh"
      }
    },
    {
      "sort": 72,
      "type": "填空题(客观)",
      "title": "【B1U8 Festivals · iWords B】【短语填空】\n走上前去\nwalk ______ to",
      "options": [
        ""
      ],
      "correct_answer": "up",
      "your_answer": "",
      "score": "0",
      "full_score": 1,
      "fill_hint": "填英文单词，小写即可；短语按原样填写",
      "memory": {
        "en": "walk up to",
        "zh": "走上前去",
        "pos": "",
        "phonetic": "",
        "pattern": "phrase_cloze",
        "unit_tag": "【B1U8 Festivals · iWords B】",
        "lang": "en",
        "hook": "短语 walk up to ↔ 走上前去（整句记，再拆关键词）",
        "fill_hint": "填英文单词，小写即可；短语按原样填写",
        "remix_pattern": "en2zh"
      }
    },
    {
      "sort": 73,
      "type": "填空题(客观)",
      "title": "【B1U8 Festivals · iWords B】【中→英】\n究竟，到底\n请填写英文：______",
      "options": [
        ""
      ],
      "correct_answer": "on earth",
      "your_answer": "",
      "score": "0",
      "full_score": 1,
      "fill_hint": "填英文单词，小写即可；短语按原样填写",
      "memory": {
        "en": "on earth",
        "zh": "究竟，到底",
        "pos": "",
        "phonetic": "",
        "pattern": "zh2en",
        "unit_tag": "【B1U8 Festivals · iWords B】",
        "lang": "en",
        "hook": "「究竟」→ on earth（7 字母，首字母 O）",
        "fill_hint": "填英文单词，小写即可；短语按原样填写",
        "remix_pattern": "en2zh"
      }
    },
    {
      "sort": 74,
      "type": "填空题(客观)",
      "title": "【B1U8 Festivals · iWords B】【词性】\ninsist  [ɪn'sɪst]  坚持，强调\n词性（填中文，如名词、动词、形容词）：______",
      "options": [
        ""
      ],
      "correct_answer": "动词;v.;v",
      "your_answer": "",
      "score": "0",
      "full_score": 1,
      "fill_hint": "填中文词性，如：名词、动词、形容词（也可填 n. / v. / adj.）",
      "memory": {
        "en": "insist",
        "zh": "坚持，强调",
        "pos": "v.",
        "phonetic": "[ɪn'sɪst]",
        "pattern": "pos",
        "unit_tag": "【B1U8 Festivals · iWords B】",
        "pos_zh": "动词",
        "lang": "pos",
        "hook": "insist 是动词，核心义：坚持",
        "fill_hint": "填中文词性，如：名词、动词、形容词（也可填 n. / v. / adj.）",
        "remix_pattern": "spell"
      }
    },
    {
      "sort": 75,
      "type": "填空题(客观)",
      "title": "【B1U8 Festivals · iWords B】【联想拼写】\n否则，不然（adv.）\noth______ 共 9 字母：______",
      "options": [
        ""
      ],
      "correct_answer": "otherwise",
      "your_answer": "",
      "score": "0",
      "full_score": 1,
      "fill_hint": "填英文单词，小写即可；短语按原样填写",
      "memory": {
        "en": "otherwise",
        "zh": "否则，不然",
        "pos": "adv.",
        "phonetic": "['ʌðəwaɪz]",
        "pattern": "assoc",
        "unit_tag": "【B1U8 Festivals · iWords B】",
        "lang": "en",
        "hook": "联想：oth______ → otherwise（否则）",
        "fill_hint": "填英文单词，小写即可；短语按原样填写",
        "remix_pattern": "en2zh"
      }
    },
    {
      "sort": 76,
      "type": "填空题(客观)",
      "title": "【B1U8 Festivals · iWords B】【短语填空】\n处置\ndo ______",
      "options": [
        ""
      ],
      "correct_answer": "with",
      "your_answer": "",
      "score": "0",
      "full_score": 1,
      "fill_hint": "填英文单词，小写即可；短语按原样填写",
      "memory": {
        "en": "do with",
        "zh": "处置",
        "pos": "",
        "phonetic": "",
        "pattern": "phrase_cloze",
        "unit_tag": "【B1U8 Festivals · iWords B】",
        "lang": "en",
        "hook": "短语 do with ↔ 处置（整句记，再拆关键词）",
        "fill_hint": "填英文单词，小写即可；短语按原样填写",
        "remix_pattern": "en2zh"
      }
    },
    {
      "sort": 77,
      "type": "填空题(客观)",
      "title": "【B1U8 Festivals · iWords B】【中→英】\n受到某人精神（或情绪）的影响\n请填写英文：______",
      "options": [
        ""
      ],
      "correct_answer": "catch one's spirit",
      "your_answer": "",
      "score": "0",
      "full_score": 1,
      "fill_hint": "填英文单词，小写即可；短语按原样填写",
      "memory": {
        "en": "catch one's spirit",
        "zh": "受到某人精神（或情绪）的影响",
        "pos": "",
        "phonetic": "",
        "pattern": "zh2en",
        "unit_tag": "【B1U8 Festivals · iWords B】",
        "lang": "en",
        "hook": "「受到某人精神（或情绪）的影响」→ catch one's spirit（16 字母，首字母 C）",
        "fill_hint": "填英文单词，小写即可；短语按原样填写",
        "remix_pattern": "en2zh"
      }
    },
    {
      "sort": 78,
      "type": "填空题(客观)",
      "title": "【B1U8 Festivals · iWords B】【拼写】\nadj. 完美的，完满的\n首字母 P，共 7 个字母：______",
      "options": [
        ""
      ],
      "correct_answer": "perfect",
      "your_answer": "",
      "score": "0",
      "full_score": 1,
      "fill_hint": "填英文单词，小写即可；短语按原样填写",
      "memory": {
        "en": "perfect",
        "zh": "完美的，完满的",
        "pos": "adj.",
        "phonetic": "['pɜːfɪkt]",
        "pattern": "spell",
        "unit_tag": "【B1U8 Festivals · iWords B】",
        "lang": "en",
        "hook": "逐字母：p-e-r-f-e-c-t（共 7 字母）",
        "fill_hint": "填英文单词，小写即可；短语按原样填写",
        "remix_pattern": "en2zh"
      }
    },
    {
      "sort": 79,
      "type": "填空题(客观)",
      "title": "【B1U8 Festivals · iWords B】【词性】\nwoods  [wʊdz]  树林\n词性（填中文，如名词、动词、形容词）：______",
      "options": [
        ""
      ],
      "correct_answer": "名词;n.;n",
      "your_answer": "",
      "score": "0",
      "full_score": 1,
      "fill_hint": "填中文词性，如：名词、动词、形容词（也可填 n. / v. / adj.）",
      "memory": {
        "en": "woods",
        "zh": "树林",
        "pos": "n.",
        "phonetic": "[wʊdz]",
        "pattern": "pos",
        "unit_tag": "【B1U8 Festivals · iWords B】",
        "pos_zh": "名词",
        "lang": "pos",
        "hook": "woods 是名词，核心义：树林",
        "fill_hint": "填中文词性，如：名词、动词、形容词（也可填 n. / v. / adj.）",
        "remix_pattern": "spell"
      }
    },
    {
      "sort": 80,
      "type": "填空题(客观)",
      "title": "【B1U8 Festivals · iWords B】【短语填空】\n呈现，具有\ntake ______",
      "options": [
        ""
      ],
      "correct_answer": "on",
      "your_answer": "",
      "score": "0",
      "full_score": 1,
      "fill_hint": "填英文单词，小写即可；短语按原样填写",
      "memory": {
        "en": "take on",
        "zh": "呈现，具有",
        "pos": "",
        "phonetic": "",
        "pattern": "phrase_cloze",
        "unit_tag": "【B1U8 Festivals · iWords B】",
        "lang": "en",
        "hook": "短语 take on ↔ 呈现（整句记，再拆关键词）",
        "fill_hint": "填英文单词，小写即可；短语按原样填写",
        "remix_pattern": "en2zh"
      }
    },
    {
      "sort": 81,
      "type": "填空题(客观)",
      "title": "【B1U8 Festivals · iWords B】【中→英】\nadj. 喜庆的，节日的  ['festɪv]\n请填写英文：______",
      "options": [
        ""
      ],
      "correct_answer": "festive",
      "your_answer": "",
      "score": "0",
      "full_score": 1,
      "fill_hint": "填英文单词，小写即可；短语按原样填写",
      "memory": {
        "en": "festive",
        "zh": "喜庆的，节日的",
        "pos": "adj.",
        "phonetic": "['festɪv]",
        "pattern": "zh2en",
        "unit_tag": "【B1U8 Festivals · iWords B】",
        "lang": "en",
        "hook": "「喜庆的」→ festive（7 字母，首字母 F）",
        "fill_hint": "填英文单词，小写即可；短语按原样填写",
        "remix_pattern": "en2zh"
      }
    },
    {
      "sort": 82,
      "type": "填空题(客观)",
      "title": "【B1U8 Festivals · iWords B】【英→中】\nactually  ['æktʃuəli]  adv.\n中文释义：______",
      "options": [
        ""
      ],
      "correct_answer": "实际上",
      "your_answer": "",
      "score": "0",
      "full_score": 1,
      "fill_hint": "填中文释义，关键词即可",
      "memory": {
        "en": "actually",
        "zh": "实际上，事实上",
        "pos": "adv.",
        "phonetic": "['æktʃuəli]",
        "pattern": "en2zh",
        "unit_tag": "【B1U8 Festivals · iWords B】",
        "lang": "zh",
        "hook": "actually = 实际上（先记中文，再反推拼写）",
        "fill_hint": "填中文释义，关键词即可",
        "remix_pattern": "zh2en"
      }
    },
    {
      "sort": 83,
      "type": "填空题(客观)",
      "title": "【B1U8 Festivals · iWords B】【拼写】\nn. 餐后甜点\n首字母 D，共 7 个字母：______",
      "options": [
        ""
      ],
      "correct_answer": "dessert",
      "your_answer": "",
      "score": "0",
      "full_score": 1,
      "fill_hint": "填英文单词，小写即可；短语按原样填写",
      "memory": {
        "en": "dessert",
        "zh": "餐后甜点",
        "pos": "n.",
        "phonetic": "[dɪ'zɜːt]",
        "pattern": "spell",
        "unit_tag": "【B1U8 Festivals · iWords B】",
        "lang": "en",
        "hook": "逐字母：d-e-s-s-e-r-t（共 7 字母）",
        "fill_hint": "填英文单词，小写即可；短语按原样填写",
        "remix_pattern": "en2zh"
      }
    },
    {
      "sort": 84,
      "type": "填空题(客观)",
      "title": "【B1U8 Festivals · iWords B】【词性】\nfinal  ['faɪnl]  最后的，最终的\n词性（填中文，如名词、动词、形容词）：______",
      "options": [
        ""
      ],
      "correct_answer": "形容词;adj.;adj",
      "your_answer": "",
      "score": "0",
      "full_score": 1,
      "fill_hint": "填中文词性，如：名词、动词、形容词（也可填 n. / v. / adj.）",
      "memory": {
        "en": "final",
        "zh": "最后的，最终的",
        "pos": "adj.",
        "phonetic": "['faɪnl]",
        "pattern": "pos",
        "unit_tag": "【B1U8 Festivals · iWords B】",
        "pos_zh": "形容词",
        "lang": "pos",
        "hook": "final 是形容词，核心义：最后的",
        "fill_hint": "填中文词性，如：名词、动词、形容词（也可填 n. / v. / adj.）",
        "remix_pattern": "spell"
      }
    },
    {
      "sort": 85,
      "type": "填空题(客观)",
      "title": "【B1U8 Festivals · iWords B】【联想拼写】\n有火焰的，燃烧的（adj.）\nfla____ 共 7 字母：______",
      "options": [
        ""
      ],
      "correct_answer": "flaming",
      "your_answer": "",
      "score": "0",
      "full_score": 1,
      "fill_hint": "填英文单词，小写即可；短语按原样填写",
      "memory": {
        "en": "flaming",
        "zh": "有火焰的，燃烧的",
        "pos": "adj.",
        "phonetic": "['fleɪmɪŋ]",
        "pattern": "assoc",
        "unit_tag": "【B1U8 Festivals · iWords B】",
        "lang": "en",
        "hook": "联想：fla____ → flaming（有火焰的）",
        "fill_hint": "填英文单词，小写即可；短语按原样填写",
        "remix_pattern": "en2zh"
      }
    },
    {
      "sort": 86,
      "type": "填空题(客观)",
      "title": "【B1U8 Festivals · iWords B】【中→英】\nn. 布丁  ['pʊdɪŋ]\n请填写英文：______",
      "options": [
        ""
      ],
      "correct_answer": "pudding",
      "your_answer": "",
      "score": "0",
      "full_score": 1,
      "fill_hint": "填英文单词，小写即可；短语按原样填写",
      "memory": {
        "en": "pudding",
        "zh": "布丁",
        "pos": "n.",
        "phonetic": "['pʊdɪŋ]",
        "pattern": "zh2en",
        "unit_tag": "【B1U8 Festivals · iWords B】",
        "lang": "en",
        "hook": "「布丁」→ pudding（7 字母，首字母 P）",
        "fill_hint": "填英文单词，小写即可；短语按原样填写",
        "remix_pattern": "en2zh"
      }
    },
    {
      "sort": 87,
      "type": "填空题(客观)",
      "title": "【B1U8 Festivals · iWords B】【英→中】\nmerry  ['meri]  adj.\n中文释义：______",
      "options": [
        ""
      ],
      "correct_answer": "欢乐的",
      "your_answer": "",
      "score": "0",
      "full_score": 1,
      "fill_hint": "填中文释义，关键词即可",
      "memory": {
        "en": "merry",
        "zh": "欢乐的，愉快的",
        "pos": "adj.",
        "phonetic": "['meri]",
        "pattern": "en2zh",
        "unit_tag": "【B1U8 Festivals · iWords B】",
        "lang": "zh",
        "hook": "merry = 欢乐的（先记中文，再反推拼写）",
        "fill_hint": "填中文释义，关键词即可",
        "remix_pattern": "zh2en"
      }
    },
    {
      "sort": 88,
      "type": "填空题(客观)",
      "title": "【B1U8 Festivals · iWords B】【短语填空】\n我的天哪！（用以表示惊奇、害怕等强烈感情）\nDear ______",
      "options": [
        ""
      ],
      "correct_answer": "me!",
      "your_answer": "",
      "score": "0",
      "full_score": 1,
      "fill_hint": "填英文单词，小写即可；短语按原样填写",
      "memory": {
        "en": "Dear me!",
        "zh": "我的天哪！（用以表示惊奇、害怕等强烈感情）",
        "pos": "",
        "phonetic": "",
        "pattern": "phrase_cloze",
        "unit_tag": "【B1U8 Festivals · iWords B】",
        "lang": "en",
        "hook": "短语 Dear me! ↔ 我的天哪！（用以表示惊奇、害怕等强烈感情）（整句记，再拆关键词）",
        "fill_hint": "填英文单词，小写即可；短语按原样填写",
        "remix_pattern": "en2zh"
      }
    },
    {
      "sort": 89,
      "type": "填空题(客观)",
      "title": "【B1U8 Festivals · iWords B】【词性】\ngasp  [ɡɑːsp]  喘息，喘着气说\n词性（填中文，如名词、动词、形容词）：______",
      "options": [
        ""
      ],
      "correct_answer": "动词;v.;v",
      "your_answer": "",
      "score": "0",
      "full_score": 1,
      "fill_hint": "填中文词性，如：名词、动词、形容词（也可填 n. / v. / adj.）",
      "memory": {
        "en": "gasp",
        "zh": "喘息，喘着气说",
        "pos": "v.",
        "phonetic": "[ɡɑːsp]",
        "pattern": "pos",
        "unit_tag": "【B1U8 Festivals · iWords B】",
        "pos_zh": "动词",
        "lang": "pos",
        "hook": "gasp 是动词，核心义：喘息",
        "fill_hint": "填中文词性，如：名词、动词、形容词（也可填 n. / v. / adj.）",
        "remix_pattern": "spell"
      }
    },
    {
      "sort": 90,
      "type": "填空题(客观)",
      "title": "【B1U8 Festivals · iWords B】【联想拼写】\n欢乐，喜悦（n.）\njo_ 共 3 字母：______",
      "options": [
        ""
      ],
      "correct_answer": "joy",
      "your_answer": "",
      "score": "0",
      "full_score": 1,
      "fill_hint": "填英文单词，小写即可；短语按原样填写",
      "memory": {
        "en": "joy",
        "zh": "欢乐，喜悦",
        "pos": "n.",
        "phonetic": "[dʒɔɪ]",
        "pattern": "assoc",
        "unit_tag": "【B1U8 Festivals · iWords B】",
        "lang": "en",
        "hook": "联想：jo_ → joy（欢乐）",
        "fill_hint": "填英文单词，小写即可；短语按原样填写",
        "remix_pattern": "en2zh"
      }
    },
    {
      "sort": 91,
      "type": "填空题(客观)",
      "title": "【B1U8 Festivals · iWords B】【拼写】\n阻止……发生，抑制\n首字母 K，共 11 个字母：______",
      "options": [
        ""
      ],
      "correct_answer": "keep ... from",
      "your_answer": "",
      "score": "0",
      "full_score": 1,
      "fill_hint": "填英文单词，小写即可；短语按原样填写",
      "memory": {
        "en": "keep ... from",
        "zh": "阻止……发生，抑制",
        "pos": "",
        "phonetic": "",
        "pattern": "spell",
        "unit_tag": "【B1U8 Festivals · iWords B】",
        "lang": "en",
        "hook": "逐字母：k-e-e-p-.-.-.-f-r-o-m（共 11 字母）",
        "fill_hint": "填英文单词，小写即可；短语按原样填写",
        "remix_pattern": "en2zh"
      }
    }
  ]
}